mcsp/__init__.py
mcsp/mcsp.cp310-win_amd64.pyd
mcsp-1.2.2.dist-info/METADATA
mcsp-1.2.2.dist-info/WHEEL
mcsp-1.2.2.dist-info/top_level.txt
mcsp-1.2.2.dist-info/RECORD
