Metadata-Version: 2.1
Name: mcsp
Version: 1.2.2
Summary: mcsp
Home-page: 
Download-URL: 
Author: sike6054
Author-email: sike6054@gmail.com
Classifier: Programming Language :: Python :: 3.10
Classifier: Operating System :: Microsoft :: Windows
Requires-Python: >=3.10, <3.11
